aishell/__init__.py
aishell/__main__.py
aishell/cli/__init__.py
aishell/cli/aishell.py
aishell/cli/cli_app.py
aishell/cli/config_aishell.py
aishell/py.typed
aishell/tests/__init__.py
aishell/tests/sample_test.py
aishell/utils/__init__.py
aishell/utils/construct_prompt.py
aishell-2023.4.16.post1.dist-info/LICENSE
aishell-2023.4.16.post1.dist-info/METADATA
aishell-2023.4.16.post1.dist-info/WHEEL
aishell-2023.4.16.post1.dist-info/entry_points.txt
aishell-2023.4.16.post1.dist-info/RECORD
