Metadata-Version: 2.1
Name: aishell
Version: 2023.4.16.post1
Summary: 
Requires-Python: >=3.9,<4.0
Classifier: Programming Language :: Python :: 3
Classifier: Programming Language :: Python :: 3.9
Classifier: Programming Language :: Python :: 3.10
Classifier: Programming Language :: Python :: 3.11
Requires-Dist: poetry (>=1.4.0,<2.0.0)
Requires-Dist: revchatgptauth (>=2023.4.16,<2024.0.0)
Requires-Dist: typer[all] (>=0.7.0,<0.8.0)
Requires-Dist: ygka (>=2023.4.16.post1,<2024.0.0)
